{"data":[{"name":"fcjyqkGrid","value":"[{\"zgj\":\"6778.31\",\"dqmc\":\"建德市\",\"cjl\":\"3\",\"spj\":\"5550\",\"kpj\":\"6778.31\",\"zdj\":\"4620.75\",\"tybm\":\"23301820000\",\"cje\":\"1894557.21\",\"pjjg\":\"5649.69\",\"ssrq\":\"20160428\",\"sssr\":\"123394.15\"},{\"zgj\":\"5638.8\",\"dqmc\":\"建德市\",\"cjl\":\"1\",\"spj\":\"5638.8\",\"kpj\":\"5638.8\",\"zdj\":\"5638.8\",\"tybm\":\"23301820000\",\"cje\":\"731747.08\",\"pjjg\":\"5638.8\",\"ssrq\":\"20160430\",\"sssr\":\"0\"},{\"zgj\":\"5000\",\"dqmc\":\"建德市\",\"cjl\":\"1\",\"spj\":\"5000\",\"kpj\":\"5000\",\"zdj\":\"5000\",\"tybm\":\"23301820000\",\"cje\":null,\"pjjg\":\"5000\",\"ssrq\":\"20160805\",\"sssr\":\"0\"},{\"zgj\":\"6952.17\",\"dqmc\":\"建德市\",\"cjl\":\"1\",\"spj\":\"6952.17\",\"kpj\":\"6952.17\",\"zdj\":\"6952.17\",\"tybm\":\"23301820000\",\"cje\":null,\"pjjg\":\"6952.17\",\"ssrq\":\"20160819\",\"sssr\":\"0\"},{\"zgj\":\"9615.38\",\"dqmc\":\"建德市\",\"cjl\":\"11\",\"spj\":\"3387.92\",\"kpj\":\"9615.38\",\"zdj\":\"1056.94\",\"tybm\":\"23301820000\",\"cje\":null,\"pjjg\":\"4758.12\",\"ssrq\":\"20160822\",\"sssr\":\"0\"},{\"zgj\":\"4440.15\",\"dqmc\":\"建德市\",\"cjl\":\"6\",\"spj\":\"3796.32\",\"kpj\":\"2885.21\",\"zdj\":\"2271.01\",\"tybm\":\"23301820000\",\"cje\":null,\"pjjg\":\"3345.7\",\"ssrq\":\"20160823\",\"sssr\":\"0\"},{\"zgj\":\"6673.21\",\"dqmc\":\"建德市\",\"cjl\":\"3\",\"spj\":\"6593.6\",\"kpj\":\"6673.21\",\"zdj\":\"6593.6\",\"tybm\":\"23301820000\",\"cje\":null,\"pjjg\":\"6633.41\",\"ssrq\":\"20160824\",\"sssr\":\"0\"},{\"zgj\":\"6307.98\",\"dqmc\":\"建德市\",\"cjl\":\"2\",\"spj\":\"5607.35\",\"kpj\":\"6307.98\",\"zdj\":\"5607.35\",\"tybm\":\"23301820000\",\"cje\":null,\"pjjg\":\"5957.67\",\"ssrq\":\"20160825\",\"sssr\":\"0\"},{\"zgj\":\"8111.94\",\"dqmc\":\"建德市\",\"cjl\":\"7\",\"spj\":\"2901.59\",\"kpj\":\"3483.33\",\"zdj\":\"2901.59\",\"tybm\":\"23301820000\",\"cje\":null,\"pjjg\":\"4711.37\",\"ssrq\":\"20160826\",\"sssr\":\"0\"},{\"zgj\":\"7850.53\",\"dqmc\":\"建德市\",\"cjl\":\"9\",\"spj\":\"5314.01\",\"kpj\":\"4434.77\",\"zdj\":\"2713.8\",\"tybm\":\"23301820000\",\"cje\":null,\"pjjg\":\"5119.99\",\"ssrq\":\"20160829\",\"sssr\":\"0\"},{\"zgj\":\"6396\",\"dqmc\":\"建德市\",\"cjl\":\"4\",\"spj\":\"4830.92\",\"kpj\":\"5175\",\"zdj\":\"4830.92\",\"tybm\":\"23301820000\",\"cje\":null,\"pjjg\":\"5394.23\",\"ssrq\":\"20160830\",\"sssr\":\"0\"},{\"zgj\":\"5907.66\",\"dqmc\":\"建德市\",\"cjl\":\"5\",\"spj\":\"2218\",\"kpj\":\"5907.66\",\"zdj\":\"1405.26\",\"tybm\":\"23301820000\",\"cje\":null,\"pjjg\":\"3256.14\",\"ssrq\":\"20160831\",\"sssr\":\"0\"},{\"zgj\":\"4772.25\",\"dqmc\":\"建德市\",\"cjl\":\"3\",\"spj\":\"2883.84\",\"kpj\":\"2145.92\",\"zdj\":\"2145.92\",\"tybm\":\"23301820000\",\"cje\":null,\"pjjg\":\"3267.34\",\"ssrq\":\"20160901\",\"sssr\":\"0\"},{\"zgj\":\"4970.52\",\"dqmc\":\"建德市\",\"cjl\":\"8\",\"spj\":\"4970.52\",\"kpj\":\"3826.65\",\"zdj\":\"1593.9\",\"tybm\":\"23301820000\",\"cje\":null,\"pjjg\":\"3505.84\",\"ssrq\":\"20160902\",\"sssr\":\"0\"},{\"zgj\":\"7939.31\",\"dqmc\":\"建德市\",\"cjl\":\"2\",\"spj\":\"7939.31\",\"kpj\":\"5207.5\",\"zdj\":\"5207.5\",\"tybm\":\"23301820000\",\"cje\":null,\"pjjg\":\"6573.41\",\"ssrq\":\"20160907\",\"sssr\":\"0\"},{\"zgj\":\"8656.65\",\"dqmc\":\"建德市\",\"cjl\":\"8\",\"spj\":\"4125.05\",\"kpj\":\"8656.65\",\"zdj\":\"1878.66\",\"tybm\":\"23301820000\",\"cje\":null,\"pjjg\":\"4221.65\",\"ssrq\":\"20160908\",\"sssr\":\"0\"},{\"zgj\":\"9954.65\",\"dqmc\":\"建德市\",\"cjl\":\"5\",\"spj\":\"9954.65\",\"kpj\":\"2059.36\",\"zdj\":\"2059.36\",\"tybm\":\"23301820000\",\"cje\":null,\"pjjg\":\"5740.52\",\"ssrq\":\"20160913\",\"sssr\":\"0\"},{\"zgj\":\"6439.5\",\"dqmc\":\"建德市\",\"cjl\":\"2\",\"spj\":\"6439.5\",\"kpj\":\"1738.83\",\"zdj\":\"1738.83\",\"tybm\":\"23301820000\",\"cje\":null,\"pjjg\":\"4089.17\",\"ssrq\":\"20160914\",\"sssr\":\"0\"},{\"zgj\":\"4926.72\",\"dqmc\":\"建德市\",\"cjl\":\"3\",\"spj\":\"1624.45\",\"kpj\":\"4926.72\",\"zdj\":\"1624.45\",\"tybm\":\"23301820000\",\"cje\":null,\"pjjg\":\"2725.21\",\"ssrq\":\"20160918\",\"sssr\":\"0\"}]","type":""}]}