{"data":[{"name":"fcjyqkGrid","value":"[{\"zgj\":\"16608.85\",\"dqmc\":\"瑞安市\",\"cjl\":\"11\",\"spj\":\"12505.68\",\"kpj\":\"9500.95\",\"zdj\":\"6286.3\",\"tybm\":\"23303810000\",\"cje\":\"11532747.2\",\"pjjg\":\"10965.99\",\"ssrq\":\"20160428\",\"sssr\":\"1004526.23\"},{\"zgj\":\"12000\",\"dqmc\":\"瑞安市\",\"cjl\":\"8\",\"spj\":\"11000\",\"kpj\":\"7837.08\",\"zdj\":\"4197.44\",\"tybm\":\"23303810000\",\"cje\":\"5579736.87\",\"pjjg\":\"8837.81\",\"ssrq\":\"20160429\",\"sssr\":\"555099.44\"},{\"zgj\":\"10000\",\"dqmc\":\"瑞安市\",\"cjl\":\"4\",\"spj\":\"10000\",\"kpj\":\"10000\",\"zdj\":\"7142.86\",\"tybm\":\"23303810000\",\"cje\":\"3000000\",\"pjjg\":\"9285.72\",\"ssrq\":\"20160430\",\"sssr\":\"271428.57\"},{\"zgj\":\"10000\",\"dqmc\":\"瑞安市\",\"cjl\":\"1\",\"spj\":\"10000\",\"kpj\":\"10000\",\"zdj\":\"10000\",\"tybm\":\"23303810000\",\"cje\":null,\"pjjg\":\"10000\",\"ssrq\":\"20160805\",\"sssr\":\"0\"},{\"zgj\":\"4713.49\",\"dqmc\":\"瑞安市\",\"cjl\":\"6\",\"spj\":\"2700.03\",\"kpj\":\"4713.49\",\"zdj\":\"2700.03\",\"tybm\":\"23303810000\",\"cje\":null,\"pjjg\":\"3706.76\",\"ssrq\":\"20160808\",\"sssr\":\"0\"},{\"zgj\":\"10000\",\"dqmc\":\"瑞安市\",\"cjl\":\"5\",\"spj\":\"3862.25\",\"kpj\":\"1142.55\",\"zdj\":\"1142.55\",\"tybm\":\"23303810000\",\"cje\":null,\"pjjg\":\"5001.6\",\"ssrq\":\"20160810\",\"sssr\":\"0\"},{\"zgj\":\"7953.5\",\"dqmc\":\"瑞安市\",\"cjl\":\"11\",\"spj\":\"1493.62\",\"kpj\":\"2657.31\",\"zdj\":\"1493.62\",\"tybm\":\"23303810000\",\"cje\":null,\"pjjg\":\"2656.12\",\"ssrq\":\"20160818\",\"sssr\":\"0\"},{\"zgj\":\"9458.14\",\"dqmc\":\"瑞安市\",\"cjl\":\"4\",\"spj\":\"1413.17\",\"kpj\":\"9458.14\",\"zdj\":\"1413.17\",\"tybm\":\"23303810000\",\"cje\":null,\"pjjg\":\"5083.01\",\"ssrq\":\"20160905\",\"sssr\":\"0\"},{\"zgj\":\"2371.07\",\"dqmc\":\"瑞安市\",\"cjl\":\"3\",\"spj\":\"2371.07\",\"kpj\":\"1400\",\"zdj\":\"1400\",\"tybm\":\"23303810000\",\"cje\":null,\"pjjg\":\"1885.54\",\"ssrq\":\"20160907\",\"sssr\":\"0\"},{\"zgj\":\"1350.01\",\"dqmc\":\"瑞安市\",\"cjl\":\"3\",\"spj\":\"1350.01\",\"kpj\":\"1350.01\",\"zdj\":\"1350.01\",\"tybm\":\"23303810000\",\"cje\":null,\"pjjg\":\"1350.01\",\"ssrq\":\"20160909\",\"sssr\":\"0\"},{\"zgj\":\"7000\",\"dqmc\":\"瑞安市\",\"cjl\":\"5\",\"spj\":\"1020.87\",\"kpj\":\"1461.67\",\"zdj\":\"1020.87\",\"tybm\":\"23303810000\",\"cje\":null,\"pjjg\":\"4120.64\",\"ssrq\":\"20160912\",\"sssr\":\"0\"},{\"zgj\":\"7268.2\",\"dqmc\":\"瑞安市\",\"cjl\":\"5\",\"spj\":\"1995.45\",\"kpj\":\"1874.46\",\"zdj\":\"1874.46\",\"tybm\":\"23303810000\",\"cje\":null,\"pjjg\":\"3712.7\",\"ssrq\":\"20160913\",\"sssr\":\"0\"}]","type":""}]}